{
    "offersInfo": [
      {
        "page": "Page d'accueil",
        "placements": [
          {
            "name": "Nouvel arrivage",
            "price": 1000,
            "duration": {
              "value": 7,
              "unit": "jours"
            }
          },
          {
            "name": "Meilleurs produits",
            "price": 1200,
            "duration": {
              "value": 7,
              "unit": "jours"
            }
          },
          {
            "name": "Soldes",
            "price": 1500,
            "duration": {
              "value": 14,
              "unit": "jours"
            }
          },
          {
            "name": "Marché algérien",
            "price": 800,
            "duration": {
              "value": 30,
              "unit": "jours"
            }
          },
          {
            "name": "Marché international",
            "price": 2000,
            "duration": {
              "value": 30,
              "unit": "jours"
            }
          },
          {
            "name": "Produit artisanal",
            "price": 900,
            "duration": {
              "value": 14,
              "unit": "jours"
            }
          },
          {
            "name": "Startups",
            "price": 750,
            "duration": {
              "value": 14,
              "unit": "jours"
            }
          }
        ]
      },
      {
        "page": "Page Art",
        "placements": [
          {
            "name": "Plein page",
            "price": 3000,
            "duration": {
              "value": 30,
              "unit": "jours"
            }
          }
        ]
      },
      {
        "page": "Page Startup",
        "placements": [
          {
            "name": "Plein page",
            "price": 2500,
            "duration": {
              "value": 30,
              "unit": "jours"
            }
          }
        ]
      },
      {
        "page": "Page Nouvel arrivage",
        "placements": [
          {
            "name": "Plein page",
            "price": 2800,
            "duration": {
              "value": 14,
              "unit": "jours"
            }
          }
        ]
      },
      {
        "page": "Page Meilleurs produits",
        "placements": [
          {
            "name": "Plein page",
            "price": 3200,
            "duration": {
              "value": 30,
              "unit": "jours"
            }
          }
        ]
      },
      {
        "page": "Page Soldes",
        "placements": [
          {
            "name": "Plein page",
            "price": 3500,
            "duration": {
              "value": 14,
              "unit": "jours"
            }
          }
        ]
      }
    ],
    "companyInfo": {
      "companyType": ["ordinaire", "art", "startup"],
      "secteur": {
        "options": ["Industrie", "Agriculture", "Construction", "ITech"],
        "isOptional": true
      },
      "marchéVisé": ["national", "international"],
      "origineDeLEntreprise": ["algérienne", "internationale"]
    }
  }